liblaf/peach/__init__.py
liblaf/peach/__init__.pyi
liblaf/peach/_version.py
liblaf/peach/_version.pyi
liblaf/peach/py.typed
liblaf/peach/constraints/__init__.py
liblaf/peach/constraints/__init__.pyi
liblaf/peach/constraints/_abc.py
liblaf/peach/constraints/_bound.py
liblaf/peach/constraints/_fixed.py
liblaf/peach/cuda/__init__.py
liblaf/peach/cuda/__init__.pyi
liblaf/peach/cuda/_available.py
liblaf/peach/functools/__init__.py
liblaf/peach/functools/__init__.pyi
liblaf/peach/functools/_descriptor.py
liblaf/peach/functools/_wrapper.py
liblaf/peach/linalg/__init__.py
liblaf/peach/linalg/__init__.pyi
liblaf/peach/linalg/abc/__init__.py
liblaf/peach/linalg/abc/__init__.pyi
liblaf/peach/linalg/abc/_solver.py
liblaf/peach/linalg/abc/_types.py
liblaf/peach/linalg/cupy/__init__.py
liblaf/peach/linalg/cupy/__init__.pyi
liblaf/peach/linalg/cupy/_base.py
liblaf/peach/linalg/cupy/_cg.py
liblaf/peach/linalg/cupy/_minres.py
liblaf/peach/linalg/cupy/_types.py
liblaf/peach/linalg/jax/__init__.py
liblaf/peach/linalg/jax/__init__.pyi
liblaf/peach/linalg/jax/_base.py
liblaf/peach/linalg/jax/_bicgstab.py
liblaf/peach/linalg/jax/_cg.py
liblaf/peach/linalg/jax/_gmres.py
liblaf/peach/linalg/jax/_types.py
liblaf/peach/linalg/misc/__init__.py
liblaf/peach/linalg/misc/__init__.pyi
liblaf/peach/linalg/misc/_composite.py
liblaf/peach/linalg/misc/_composite_types.py
liblaf/peach/linalg/scipy/__init__.py
liblaf/peach/linalg/scipy/__init__.pyi
liblaf/peach/linalg/scipy/_base.py
liblaf/peach/linalg/scipy/_bicg.py
liblaf/peach/linalg/scipy/_bicgstab.py
liblaf/peach/linalg/scipy/_cg.py
liblaf/peach/linalg/scipy/_minres.py
liblaf/peach/linalg/scipy/_types.py
liblaf/peach/linalg/system/__init__.py
liblaf/peach/linalg/system/__init__.pyi
liblaf/peach/linalg/system/_system.py
liblaf/peach/linalg/utils/__init__.py
liblaf/peach/linalg/utils/__init__.pyi
liblaf/peach/linalg/utils/_residual.py
liblaf/peach/math/__init__.py
liblaf/peach/math/__init__.pyi
liblaf/peach/math/_hess_prod.py
liblaf_peach-0.7.19.dist-info/METADATA
liblaf_peach-0.7.19.dist-info/WHEEL
liblaf_peach-0.7.19.dist-info/RECORD
