Metadata-Version: 2.4
Name: liblaf-peach
Version: 0.7.19
Project-URL: Changelog, https://github.com/liblaf/peach/blob/main/CHANGELOG.md
Project-URL: Documentation, https://liblaf.github.io/peach/
Project-URL: Funding, https://github.com/liblaf/peach?sponsor=1
Project-URL: Homepage, https://github.com/liblaf/peach
Project-URL: Issue Tracker, https://github.com/liblaf/peach/issues
Project-URL: Release Notes, https://github.com/liblaf/peach/releases
Project-URL: Source Code, https://github.com/liblaf/peach
Author-email: liblaf <30631553+liblaf@users.noreply.github.com>
License-Expression: MIT
Classifier: Development Status :: 4 - Beta
Classifier: Intended Audience :: Developers
Classifier: License :: OSI Approved
Classifier: License :: OSI Approved :: MIT License
Classifier: Operating System :: OS Independent
Classifier: Programming Language :: Python
Classifier: Programming Language :: Python :: 3
Classifier: Programming Language :: Python :: 3.12
Classifier: Programming Language :: Python :: 3.13
Classifier: Typing :: Typed
Requires-Python: >=3.12
Requires-Dist: attrs<26,>=25
Requires-Dist: cytoolz<2,>=1
Requires-Dist: equinox<0.14,>=0.13
Requires-Dist: jax<0.9,>=0.8
Requires-Dist: jaxtyping<0.4,>=0.3
Requires-Dist: lazy-loader<0.5,>=0.4
Requires-Dist: liblaf-grapes<9,>=8
Requires-Dist: lineax<0.0.9,>=0.0.8
Requires-Dist: more-itertools<11,>=10
Requires-Dist: numpy<3,>=2
Requires-Dist: optax<0.3,>=0.2
Requires-Dist: pylops<3,>=2
Requires-Dist: scipy<2,>=1
Requires-Dist: wrapt<3,>=2
Provides-Extra: cuda12
Requires-Dist: cupy-cuda12x<14,>=13; extra == 'cuda12'
Requires-Dist: jax[cuda12]<0.9,>=0.8; extra == 'cuda12'
Provides-Extra: cuda13
Requires-Dist: cupy-cuda13x<14,>=13; extra == 'cuda13'
Requires-Dist: jax[cuda13]<0.9,>=0.8; extra == 'cuda13'
